Metadata-Version: 1.1
Name: textpipeliner
Version: 0.3.1
Summary: textpipeliner - library for extracting specific words from sentences of a document
Home-page: https://github.com/krzysiekfonal/textpipeliner
Author: Krzysztof Fonal
Author-email: krzysiek.fonal@gmail.com
License: MIT
Keywords: nlp text mining text extraction
Platform: UNKNOWN
Classifier: Development Status :: 3 - Alpha
Classifier: License :: OSI Approved :: MIT License
Classifier: Programming Language :: Python :: 3.5
Classifier: Topic :: Scientific/Engineering :: Artificial Intelligence
Classifier: Intended Audience :: Science/Research
